README.md
setup.py
kubessh/__init__.py
kubessh/__main__.py
kubessh/app.py
kubessh/cleanup.py
kubessh/pod.py
kubessh/serialization.py
kubessh/server.py
kubessh/tcp.py
kubessh.egg-info/PKG-INFO
kubessh.egg-info/SOURCES.txt
kubessh.egg-info/dependency_links.txt
kubessh.egg-info/entry_points.txt
kubessh.egg-info/requires.txt
kubessh.egg-info/top_level.txt
kubessh/authentication/__init__.py
kubessh/authentication/dummy.py
kubessh/authentication/github.py
kubessh/authentication/gitlab.py